sagan/__init__.py
sagan/arducam.py
sagan/baro.py
sagan/i2c.py
sagan/imu.py
sagan/leds.py
sagan/rgb_ir.py
sagan/rtc.py
sagan/temperature.py
sagan/uva.py
saganvm-1.2.5.dist-info/METADATA
saganvm-1.2.5.dist-info/WHEEL
saganvm-1.2.5.dist-info/top_level.txt
saganvm-1.2.5.dist-info/RECORD
