Metadata-Version: 2.1
Name: saganvm
Version: 1.2.5
Summary: Python library for simulating experiment results
Home-page: 
Author: T A H Smith, A W Collins, Jeff Trotman
Author-email: jtrotman@dreamup.org
